GrowthShenruqianchuQuanzhanGongchengshi/README.md
GrowthShenruqianchuQuanzhanGongchengshi/__init__.py
GrowthShenruqianchuQuanzhanGongchengshi/__main__.py
GrowthShenruqianchuQuanzhanGongchengshi/file.epub
GrowthShenruqianchuQuanzhanGongchengshi/index.html
GrowthShenruqianchuQuanzhanGongchengshi/css/__init__.py
GrowthShenruqianchuQuanzhanGongchengshi/css/annotations.css
GrowthShenruqianchuQuanzhanGongchengshi/css/main.css
GrowthShenruqianchuQuanzhanGongchengshi/css/normalize.css
GrowthShenruqianchuQuanzhanGongchengshi/css/popup.css
GrowthShenruqianchuQuanzhanGongchengshi/font/__init__.py
GrowthShenruqianchuQuanzhanGongchengshi/font/fontello.eot
GrowthShenruqianchuQuanzhanGongchengshi/font/fontello.svg
GrowthShenruqianchuQuanzhanGongchengshi/font/fontello.ttf
GrowthShenruqianchuQuanzhanGongchengshi/font/fontello.woff
GrowthShenruqianchuQuanzhanGongchengshi/img/__init__.py
GrowthShenruqianchuQuanzhanGongchengshi/img/annotator-glyph-sprite.png
GrowthShenruqianchuQuanzhanGongchengshi/img/annotator-icon-sprite.png
GrowthShenruqianchuQuanzhanGongchengshi/img/apple-touch-icon.png
GrowthShenruqianchuQuanzhanGongchengshi/img/cancelfullscreen.png
GrowthShenruqianchuQuanzhanGongchengshi/img/close.png
GrowthShenruqianchuQuanzhanGongchengshi/img/fullscreen.png
GrowthShenruqianchuQuanzhanGongchengshi/img/loader.gif
GrowthShenruqianchuQuanzhanGongchengshi/img/menu-icon.png
GrowthShenruqianchuQuanzhanGongchengshi/img/save.png
GrowthShenruqianchuQuanzhanGongchengshi/img/saved.png
GrowthShenruqianchuQuanzhanGongchengshi/img/settings-s.png
GrowthShenruqianchuQuanzhanGongchengshi/img/settings.png
GrowthShenruqianchuQuanzhanGongchengshi/img/star.png
GrowthShenruqianchuQuanzhanGongchengshi/js/__init__.py
GrowthShenruqianchuQuanzhanGongchengshi/js/epub.js
GrowthShenruqianchuQuanzhanGongchengshi/js/epub.min.js
GrowthShenruqianchuQuanzhanGongchengshi/js/epub.min.map
GrowthShenruqianchuQuanzhanGongchengshi/js/hooks.min.js
GrowthShenruqianchuQuanzhanGongchengshi/js/hooks.min.map
growth_shenruqianchu_quanzhan_gongchengshi-2024.3.1.0.dist-info/METADATA
growth_shenruqianchu_quanzhan_gongchengshi-2024.3.1.0.dist-info/WHEEL
growth_shenruqianchu_quanzhan_gongchengshi-2024.3.1.0.dist-info/entry_points.txt
growth_shenruqianchu_quanzhan_gongchengshi-2024.3.1.0.dist-info/top_level.txt
growth_shenruqianchu_quanzhan_gongchengshi-2024.3.1.0.dist-info/RECORD
